crackmnist/__init__.py
crackmnist/dataset.py
crackmnist/info.py
crackmnist/loss.py
crackmnist/nets.py
crackmnist/transforms.py
crackmnist-1.0.0.dist-info/LICENSE
crackmnist-1.0.0.dist-info/METADATA
crackmnist-1.0.0.dist-info/WHEEL
crackmnist-1.0.0.dist-info/top_level.txt
crackmnist-1.0.0.dist-info/RECORD
