Metadata-Version: 2.2
Name: crackmnist
Version: 1.0.0
Summary: CrackMNIST - A Large-Scale Dataset for Crack Tip Detection in Digital Image Correlation Data
Author: Erik Schultheis, Florian Paysan, Ferdinand Dömling, Eric Dietrich
Author-email: David Melching <David.Melching@dlr.de>, Eric Breitbarth <Eric.Breitbarth@dlr.de>
License: MIT License
Project-URL: Repository, https://github.com/dlr-wf/crackmnist/
Project-URL: Issues, https://github.com/dlr-wf/crackmnist/issues
Keywords: MNIST,Crack Tip Detection,Fatigue,Digital Image Correlation
Classifier: Programming Language :: Python :: 3
Requires-Python: >=3.8
License-File: LICENSE
Requires-Dist: torch~=2.5.1
Requires-Dist: numpy~=2.1.3
Requires-Dist: torchvision~=0.20.1
Requires-Dist: alive-progress~=3.2.0
Requires-Dist: h5py~=3.12.1
